LICENSE
MANIFEST.in
README.md
setup.py
lineprotocol/__init__.py
lineprotocol/lineprotocol.py
lineprotocol.egg-info/PKG-INFO
lineprotocol.egg-info/SOURCES.txt
lineprotocol.egg-info/dependency_links.txt
lineprotocol.egg-info/not-zip-safe
lineprotocol.egg-info/top_level.txt
tests/__init__.py
tests/__init__.pyc
tests/smoke_test.py
tests/smoke_test.pyc
tests/smoketest.pyc