Metadata-Version: 1.0
Name: lineprotocol
Version: 0.1.dev0
Summary: Export data to InfluxDB's Line Protocol format
Home-page: https://github.com/qn7o/lineprotocol
Author: Antonin Bourguignon
Author-email: antonin.bourguignon@gmail.com
License: MIT
Platform: UNKNOWN
